dailycheckin_liang/__init__.py
dailycheckin_liang/__version__.py
dailycheckin_liang/configs.py
dailycheckin_liang/main.py
dailycheckin_liang/acfun/__init__.py
dailycheckin_liang/acfun/main.py
dailycheckin_liang/aliyun/__init__.py
dailycheckin_liang/aliyun/main.py
dailycheckin_liang/aolaxing/__init__.py
dailycheckin_liang/aolaxing/main.py
dailycheckin_liang/baidu/__init__.py
dailycheckin_liang/baidu/main.py
dailycheckin_liang/bilibili/__init__.py
dailycheckin_liang/bilibili/main.py
dailycheckin_liang/enshan/__init__.py
dailycheckin_liang/enshan/main.py
dailycheckin_liang/imaotai/__init__.py
dailycheckin_liang/imaotai/main.py
dailycheckin_liang/iqiyi/__init__.py
dailycheckin_liang/iqiyi/main.py
dailycheckin_liang/kgqq/__init__.py
dailycheckin_liang/kgqq/main.py
dailycheckin_liang/mimotion/__init__.py
dailycheckin_liang/mimotion/main.py
dailycheckin_liang/smzdm/__init__.py
dailycheckin_liang/smzdm/main.py
dailycheckin_liang/test/__init__.py
dailycheckin_liang/test/main.py
dailycheckin_liang/tieba/__init__.py
dailycheckin_liang/tieba/main.py
dailycheckin_liang/utils/__init__.py
dailycheckin_liang/utils/message.py
dailycheckin_liang/v2ex/__init__.py
dailycheckin_liang/v2ex/main.py
dailycheckin_liang/youdao/__init__.py
dailycheckin_liang/youdao/main.py
dailycheckin_liang-25.1.602.dist-info/LICENSE
dailycheckin_liang-25.1.602.dist-info/METADATA
dailycheckin_liang-25.1.602.dist-info/WHEEL
dailycheckin_liang-25.1.602.dist-info/entry_points.txt
dailycheckin_liang-25.1.602.dist-info/top_level.txt
dailycheckin_liang-25.1.602.dist-info/RECORD
