Metadata-Version: 2.1
Name: dailycheckin-liang
Version: 25.1.602
Summary: dailycheckin-liang
Home-page: https://github.com/LiangGame/
Author: LiangGame
Author-email: 1924196944@qq.com
License: MIT
Project-URL: Documentation, https://github.com/LiangGame/dailycheckin/
Classifier: License :: OSI Approved :: MIT License
Classifier: Programming Language :: Python :: 3.9
Classifier: Programming Language :: Python :: 3.10
Classifier: Programming Language :: Python :: Implementation :: CPython
Classifier: Programming Language :: Python :: Implementation :: PyPy
Requires-Python: >=3.9.0
License-File: LICENSE
Requires-Dist: pycryptodome==3.17
Requires-Dist: requests~=2.25.1
Requires-Dist: rsa~=4.0
Requires-Dist: urllib3~=1.26.2
